MANIFEST.in
README.rst
ebi_metagenomics
setup.cfg
setup.py
ebisearch/__init__.py
ebisearch/__main__.py
ebisearch.egg-info/PKG-INFO
ebisearch.egg-info/SOURCES.txt
ebisearch.egg-info/dependency_links.txt
ebisearch.egg-info/entry_points.txt
ebisearch.egg-info/requires.txt
ebisearch.egg-info/top_level.txt
ebisearch_data/__init__.py
ebisearch_data/ebi_metagenomics_run_data.json